{
    "location": "cambridge_ma",
    "budget": {
        "initial": 15000,
        "monthly": 500
    },
    "allow_grid": true,
    "products": [
    {
      "name":  "smallsolar",
      "utility_type":  "electricity",
      "energy_type": "solar",
      "opening_cost":  1000,
      "incremental_cost": 100,
      "maintenance_cost": 0,
      "capacity": 2,
      "amortization": 30
    },
    {
      "name": "smallbattery",
      "utility_type": "electricity",
      "energy_type": "storage",
      "opening_cost": 100,
      "incremental_cost": 100,
      "maintenance_cost": 0,
      "capacity": 2,
      "amortization": 30
    },
          {
      "name": "smallwind",
      "utility_type": "electricity",
      "energy_type": "wind",
      "opening_cost": 1500,
      "incremental_cost": 100,
      "maintenance_cost": 0,
      "capacity": 1,
      "amortization": 30
    }
    ]
}